README.md
setup.py
client/__init__.py
client/cli.py
client/android_ios/__init__.py
client/android_ios/run_sync_devices_.py
client/example/__init__.py
client/example/sweetest_example.py
super_sweetest/__init__.py
super_sweetest/autotest.py
super_sweetest/config.py
super_sweetest/data.py
super_sweetest/database.py
super_sweetest/elements.py
super_sweetest/globals.py
super_sweetest/junit.py
super_sweetest/locator.py
super_sweetest/log.py
super_sweetest/parse.py
super_sweetest/report.py
super_sweetest/snapshot.py
super_sweetest/testcase.py
super_sweetest/testsuite.py
super_sweetest/utility.py
super_sweetest/windows.py
super_sweetest.egg-info/PKG-INFO
super_sweetest.egg-info/SOURCES.txt
super_sweetest.egg-info/dependency_links.txt
super_sweetest.egg-info/entry_points.txt
super_sweetest.egg-info/requires.txt
super_sweetest.egg-info/top_level.txt
super_sweetest/client/__init__.py
super_sweetest/client/app/__init__.py
super_sweetest/client/app/android_ios_cli.py
super_sweetest/client/app/run_sync_device.py
super_sweetest/client/app/app_package/__init__.py
super_sweetest/client/app/app_package/run_android_ios.py
super_sweetest/client/app/copy_file/__init__.py
super_sweetest/client/app/copy_file/run_this.py
super_sweetest/client/app/copy_file/test_case.py
super_sweetest/client/mqtt/__init__.py
super_sweetest/client/mqtt/api_mqtt_cli.py
super_sweetest/client/mqtt/copy_file/__init__.py
super_sweetest/client/mqtt/copy_file/run_this.py
super_sweetest/client/mqtt/copy_file/test_case.py
super_sweetest/client/mqtt/mqtt_package/__init__.py
super_sweetest/client/mqtt/mqtt_package/run_api_mqtt.py
super_sweetest/keywords/__init__.py
super_sweetest/keywords/air_mobile.py
super_sweetest/keywords/common.py
super_sweetest/keywords/files.py
super_sweetest/keywords/http.py
super_sweetest/keywords/mobile.py
super_sweetest/keywords/mqtt.py
super_sweetest/keywords/web.py
super_sweetest/keywords/windows.py
super_sweetest/lib/__init__.py
super_sweetest/lib/c.py
super_sweetest/lib/func.py
super_sweetest/lib/http_handle.py
super_sweetest/lib/u.py
super_sweetest/servers/__init__.py
super_sweetest/servers/ai_server.py
super_sweetest/servers/air_android.py
super_sweetest/servers/air_ios.py
super_sweetest/servers/cmd_server.py
