Metadata-Version: 1.0
Name: super-sweetest
Version: 1.2.3.4.5
Summary: automation tools
Home-page: http://github.com/SahalaProject/super_sweetest
Author: liyubin
Author-email: 1399393088@qq.com
License: MIT Licence
Keywords: pip,super_sweetest,featureextraction
Platform: any
